{ "compressionlevel":-1,
 "height":25,
 "infinite":false,
 "layers":[
        {
         "data":[0, 0, 0, 0, 0, 0, 0, 0, 0, 0, 0, 0, 0, 0, 0, 0, 0, 0, 0, 0, 0, 0, 0, 0, 0, 0, 0, 0, 0, 0, 0, 0, 0, 0, 0, 0, 0, 0, 0, 0,
            0, 0, 0, 0, 0, 0, 0, 0, 0, 0, 0, 0, 0, 0, 0, 0, 0, 0, 0, 0, 0, 0, 0, 0, 0, 0, 0, 0, 0, 0, 0, 0, 0, 0, 0, 0, 0, 0, 0, 0,
            0, 0, 0, 0, 0, 0, 0, 0, 0, 0, 0, 0, 0, 0, 0, 0, 0, 0, 0, 0, 0, 0, 0, 0, 0, 0, 0, 0, 0, 0, 0, 0, 0, 0, 0, 0, 0, 0, 0, 0,
            0, 0, 0, 0, 0, 0, 0, 0, 0, 0, 0, 0, 0, 0, 0, 0, 0, 0, 0, 0, 0, 0, 0, 0, 0, 0, 0, 0, 0, 0, 0, 0, 0, 0, 0, 0, 0, 0, 0, 0,
            0, 0, 0, 0, 0, 0, 0, 0, 0, 0, 0, 0, 0, 0, 0, 0, 0, 0, 0, 0, 0, 0, 0, 0, 0, 0, 0, 0, 0, 0, 0, 0, 0, 0, 0, 0, 0, 0, 0, 0,
            0, 0, 0, 0, 0, 0, 0, 0, 0, 0, 0, 0, 0, 0, 0, 0, 0, 0, 0, 0, 0, 0, 0, 0, 0, 0, 0, 0, 0, 0, 0, 0, 0, 0, 0, 0, 0, 0, 0, 0,
            0, 0, 0, 0, 0, 0, 0, 0, 0, 0, 0, 0, 0, 0, 0, 0, 0, 0, 0, 0, 0, 0, 0, 0, 0, 0, 0, 0, 0, 0, 0, 0, 0, 0, 0, 0, 0, 0, 0, 0,
            0, 0, 0, 0, 0, 0, 0, 0, 0, 0, 0, 0, 0, 0, 0, 0, 0, 0, 0, 0, 0, 0, 0, 0, 0, 0, 0, 0, 0, 0, 0, 0, 0, 0, 0, 0, 0, 0, 0, 0,
            0, 0, 0, 0, 0, 0, 0, 0, 0, 0, 0, 0, 0, 0, 0, 0, 0, 0, 0, 0, 0, 0, 0, 0, 0, 0, 0, 0, 0, 0, 0, 0, 0, 0, 0, 0, 0, 0, 0, 0,
            0, 0, 0, 0, 0, 0, 0, 0, 0, 0, 0, 0, 0, 0, 0, 0, 0, 0, 0, 0, 0, 0, 0, 0, 0, 0, 0, 0, 0, 0, 0, 0, 0, 0, 0, 0, 0, 0, 0, 0,
            0, 0, 0, 0, 0, 0, 0, 0, 0, 0, 0, 0, 0, 0, 0, 0, 0, 0, 0, 0, 0, 0, 0, 0, 0, 0, 0, 0, 0, 0, 0, 0, 0, 0, 0, 0, 0, 0, 0, 0,
            0, 0, 0, 0, 0, 0, 0, 0, 0, 0, 0, 0, 0, 0, 0, 0, 0, 0, 0, 0, 0, 0, 0, 0, 0, 0, 0, 0, 0, 0, 0, 0, 0, 0, 0, 0, 0, 0, 0, 0,
            0, 0, 0, 0, 0, 0, 0, 0, 0, 0, 0, 0, 0, 0, 0, 0, 0, 0, 0, 0, 0, 0, 0, 0, 0, 0, 0, 0, 0, 0, 0, 0, 0, 0, 0, 0, 0, 0, 0, 0,
            0, 0, 0, 0, 0, 0, 0, 0, 0, 0, 0, 0, 0, 0, 0, 0, 0, 0, 0, 0, 0, 0, 0, 0, 0, 0, 0, 0, 0, 0, 0, 0, 0, 0, 0, 0, 0, 0, 0, 0,
            0, 0, 0, 0, 0, 0, 0, 0, 0, 0, 0, 0, 0, 0, 0, 0, 0, 0, 0, 0, 0, 0, 0, 0, 0, 0, 0, 0, 0, 0, 0, 0, 0, 0, 0, 0, 0, 0, 0, 0,
            0, 0, 0, 0, 0, 0, 0, 0, 0, 0, 0, 0, 0, 0, 0, 0, 0, 0, 0, 0, 0, 0, 0, 0, 0, 0, 0, 0, 0, 0, 0, 0, 0, 0, 0, 0, 0, 0, 0, 0,
            0, 0, 0, 0, 0, 0, 0, 0, 0, 0, 0, 0, 0, 0, 0, 0, 0, 0, 0, 0, 0, 0, 0, 0, 0, 0, 0, 0, 0, 0, 0, 0, 0, 0, 0, 0, 0, 0, 0, 0,
            0, 0, 0, 0, 0, 0, 0, 0, 0, 0, 0, 0, 0, 0, 0, 0, 0, 0, 0, 0, 0, 0, 0, 0, 0, 0, 0, 0, 0, 0, 0, 0, 0, 0, 0, 0, 0, 0, 0, 0,
            0, 0, 0, 0, 0, 0, 0, 0, 0, 0, 0, 0, 0, 0, 0, 0, 0, 0, 0, 0, 0, 0, 0, 0, 0, 0, 0, 0, 0, 0, 0, 0, 0, 0, 0, 0, 0, 0, 0, 0,
            0, 0, 0, 0, 0, 0, 0, 0, 0, 0, 0, 0, 0, 0, 0, 0, 0, 0, 0, 0, 0, 0, 0, 0, 0, 0, 0, 0, 0, 0, 0, 0, 0, 0, 0, 0, 0, 0, 0, 0,
            0, 0, 0, 0, 0, 0, 0, 0, 0, 0, 0, 0, 0, 0, 0, 0, 0, 0, 0, 0, 0, 0, 0, 0, 0, 0, 0, 0, 0, 0, 0, 0, 0, 0, 0, 0, 0, 0, 0, 0,
            0, 0, 0, 0, 0, 0, 0, 0, 0, 0, 0, 0, 0, 0, 0, 0, 0, 0, 0, 0, 0, 0, 0, 0, 0, 0, 0, 0, 0, 0, 0, 0, 0, 0, 0, 0, 0, 0, 0, 0,
            0, 0, 0, 0, 0, 0, 0, 0, 0, 0, 0, 0, 0, 0, 0, 0, 0, 0, 0, 0, 0, 0, 0, 0, 0, 0, 0, 0, 0, 0, 0, 0, 0, 0, 0, 0, 0, 0, 0, 0,
            0, 0, 0, 0, 0, 0, 0, 0, 0, 0, 0, 0, 0, 0, 0, 0, 0, 0, 0, 0, 0, 0, 0, 0, 0, 0, 0, 0, 0, 0, 0, 0, 0, 0, 0, 0, 0, 0, 0, 0,
            0, 0, 0, 0, 0, 0, 0, 0, 0, 0, 0, 0, 0, 0, 0, 0, 0, 0, 0, 0, 0, 0, 0, 0, 0, 0, 0, 0, 0, 0, 0, 0, 0, 0, 0, 0, 0, 0, 0, 0],
         "height":25,
         "id":2,
         "name":"Layer1",
         "opacity":1,
         "type":"tilelayer",
         "visible":true,
         "width":40,
         "x":0,
         "y":0
        }, 
        {
         "draworder":"topdown",
         "id":3,
         "name":"Objects",
         "objects":[
                {
                 "height":0,
                 "id":1,
                 "name":"",
                 "point":true,
                 "properties":[
                        {
                         "name":"ring",
                         "type":"bool",
                         "value":true
                        }],
                 "rotation":0,
                 "type":"",
                 "visible":true,
                 "width":0,
                 "x":749.333333333333,
                 "y":313.333333333333
                }, 
                {
                 "height":0,
                 "id":2,
                 "name":"",
                 "point":true,
                 "properties":[
                        {
                         "name":"ring",
                         "type":"bool",
                         "value":true
                        }],
                 "rotation":0,
                 "type":"",
                 "visible":true,
                 "width":0,
                 "x":782.333333333333,
                 "y":312.333333333333
                }, 
                {
                 "height":0,
                 "id":3,
                 "name":"",
                 "point":true,
                 "properties":[
                        {
                         "name":"ring",
                         "type":"bool",
                         "value":true
                        }],
                 "rotation":0,
                 "type":"",
                 "visible":true,
                 "width":0,
                 "x":812.333333333333,
                 "y":311.333333333333
                }, 
                {
                 "height":0,
                 "id":4,
                 "name":"",
                 "point":true,
                 "properties":[
                        {
                         "name":"ring",
                         "type":"bool",
                         "value":true
                        }],
                 "rotation":0,
                 "type":"",
                 "visible":true,
                 "width":0,
                 "x":844.333333333333,
                 "y":312.333333333333
                }, 
                {
                 "height":0,
                 "id":5,
                 "name":"",
                 "point":true,
                 "properties":[
                        {
                         "name":"ring",
                         "type":"bool",
                         "value":true
                        }],
                 "rotation":0,
                 "type":"",
                 "visible":true,
                 "width":0,
                 "x":876.333333333333,
                 "y":311.333333333333
                }, 
                {
                 "height":0,
                 "id":6,
                 "name":"",
                 "point":true,
                 "properties":[
                        {
                         "name":"ring",
                         "type":"bool",
                         "value":true
                        }],
                 "rotation":0,
                 "type":"",
                 "visible":true,
                 "width":0,
                 "x":908.333333333333,
                 "y":310.333333333333
                }, 
                {
                 "height":0,
                 "id":7,
                 "name":"",
                 "point":true,
                 "properties":[
                        {
                         "name":"ring",
                         "type":"bool",
                         "value":true
                        }],
                 "rotation":0,
                 "type":"",
                 "visible":true,
                 "width":0,
                 "x":940.333333333333,
                 "y":310.333333333333
                }],
         "opacity":1,
         "type":"objectgroup",
         "visible":true,
         "x":0,
         "y":0
        }, 
        {
         "data":[0, 0, 0, 0, 0, 0, 0, 0, 0, 0, 0, 0, 0, 0, 0, 0, 0, 0, 0, 0, 0, 0, 0, 0, 0, 0, 0, 0, 0, 0, 0, 0, 0, 0, 0, 0, 0, 0, 0, 0,
            0, 0, 0, 0, 0, 0, 0, 0, 0, 0, 0, 0, 0, 0, 0, 0, 0, 0, 0, 0, 0, 0, 0, 0, 0, 0, 0, 0, 0, 0, 0, 0, 0, 0, 0, 0, 0, 0, 0, 0,
            0, 0, 0, 0, 0, 0, 0, 0, 0, 0, 0, 0, 0, 0, 0, 0, 0, 0, 0, 0, 0, 0, 0, 0, 0, 0, 0, 0, 0, 0, 0, 0, 0, 0, 0, 0, 0, 0, 0, 0,
            0, 0, 0, 0, 0, 0, 0, 0, 0, 0, 0, 0, 0, 0, 0, 0, 0, 0, 0, 0, 0, 0, 0, 0, 0, 0, 0, 0, 0, 0, 0, 0, 0, 0, 0, 0, 0, 0, 0, 0,
            0, 0, 0, 0, 0, 0, 0, 0, 0, 0, 0, 0, 0, 0, 0, 0, 0, 0, 0, 0, 0, 0, 0, 0, 0, 0, 0, 0, 0, 0, 0, 0, 0, 0, 0, 0, 0, 0, 0, 0,
            0, 0, 0, 0, 0, 0, 0, 0, 0, 0, 0, 0, 0, 0, 0, 0, 0, 0, 0, 0, 0, 0, 0, 0, 0, 0, 0, 0, 0, 0, 0, 0, 0, 0, 0, 0, 0, 0, 0, 0,
            0, 0, 0, 0, 0, 0, 0, 0, 0, 0, 0, 0, 0, 0, 0, 0, 0, 0, 0, 0, 0, 0, 0, 0, 0, 0, 0, 0, 0, 0, 0, 0, 0, 0, 0, 0, 0, 0, 0, 0,
            0, 0, 0, 0, 0, 0, 0, 0, 0, 0, 0, 0, 0, 0, 0, 0, 0, 0, 0, 0, 0, 0, 0, 0, 0, 0, 0, 0, 0, 0, 0, 0, 0, 0, 0, 0, 0, 0, 0, 0,
            0, 0, 0, 0, 0, 0, 0, 0, 0, 0, 0, 0, 0, 0, 0, 0, 0, 0, 0, 0, 0, 0, 0, 0, 0, 0, 0, 0, 0, 0, 0, 0, 0, 0, 0, 0, 0, 0, 0, 0,
            0, 0, 0, 0, 0, 0, 0, 0, 0, 0, 0, 0, 0, 0, 0, 0, 0, 0, 0, 0, 0, 0, 0, 0, 0, 0, 0, 0, 0, 0, 0, 0, 0, 0, 0, 0, 0, 0, 0, 0,
            0, 0, 0, 0, 0, 0, 0, 0, 0, 0, 0, 0, 0, 0, 0, 0, 0, 0, 0, 0, 0, 0, 0, 0, 0, 0, 0, 0, 0, 0, 0, 0, 0, 0, 0, 0, 0, 0, 0, 0,
            0, 0, 0, 0, 0, 0, 0, 0, 0, 0, 0, 0, 0, 0, 0, 0, 0, 0, 0, 0, 13, 13, 13, 13, 13, 13, 13, 13, 13, 13, 13, 13, 13, 0, 0, 0, 0, 0, 0, 0,
            0, 0, 0, 0, 0, 0, 0, 0, 0, 0, 0, 0, 0, 0, 0, 0, 0, 0, 0, 0, 5, 5, 5, 5, 5, 5, 5, 5, 5, 5, 5, 5, 5, 0, 0, 0, 0, 0, 0, 0,
            0, 0, 0, 0, 0, 0, 0, 0, 0, 0, 0, 0, 0, 0, 0, 0, 0, 0, 0, 0, 5, 5, 5, 5, 5, 5, 5, 5, 5, 5, 5, 5, 5, 0, 0, 0, 0, 0, 0, 0,
            0, 0, 0, 0, 0, 0, 0, 0, 0, 0, 0, 0, 0, 0, 0, 0, 0, 0, 0, 0, 11, 5, 5, 5, 5, 5, 5, 5, 5, 5, 5, 5, 17, 0, 0, 0, 0, 0, 0, 0,
            0, 0, 0, 0, 0, 0, 0, 0, 0, 0, 0, 0, 0, 0, 0, 0, 0, 0, 0, 0, 0, 0, 0, 0, 0, 0, 0, 0, 0, 0, 0, 0, 0, 0, 0, 0, 0, 0, 0, 0,
            0, 0, 0, 0, 0, 0, 0, 0, 0, 0, 0, 0, 0, 37, 0, 0, 0, 0, 0, 0, 0, 0, 0, 0, 0, 0, 0, 0, 0, 0, 0, 0, 0, 0, 0, 0, 0, 0, 0, 0,
            0, 0, 0, 0, 0, 0, 0, 0, 0, 0, 0, 0, 37, 5, 0, 0, 0, 0, 0, 0, 0, 0, 0, 0, 0, 0, 0, 0, 0, 0, 0, 0, 0, 0, 0, 0, 0, 0, 0, 0,
            0, 0, 0, 0, 0, 0, 0, 0, 0, 0, 0, 37, 5, 5, 0, 0, 0, 0, 0, 0, 0, 0, 0, 0, 0, 0, 0, 0, 0, 0, 0, 0, 0, 0, 0, 0, 0, 0, 0, 0,
            0, 0, 0, 0, 0, 0, 0, 0, 0, 0, 37, 5, 5, 5, 0, 0, 0, 0, 0, 0, 0, 0, 0, 0, 0, 0, 0, 0, 0, 0, 0, 0, 0, 0, 0, 0, 0, 0, 0, 0,
            0, 0, 0, 0, 0, 0, 0, 0, 0, 37, 5, 5, 5, 5, 0, 0, 0, 0, 0, 0, 0, 0, 0, 0, 0, 0, 0, 0, 0, 0, 0, 0, 0, 0, 0, 0, 0, 0, 0, 0,
            13, 13, 13, 13, 13, 13, 13, 13, 13, 5, 5, 5, 5, 5, 13, 13, 13, 13, 13, 13, 13, 13, 13, 13, 13, 13, 13, 13, 13, 13, 13, 13, 13, 13, 13, 13, 13, 13, 13, 13,
            5, 5, 5, 5, 5, 5, 5, 5, 5, 5, 5, 5, 5, 5, 5, 5, 5, 5, 5, 5, 5, 5, 5, 5, 5, 5, 5, 5, 5, 5, 5, 5, 5, 5, 5, 5, 5, 5, 5, 5,
            5, 5, 5, 5, 5, 5, 5, 5, 5, 5, 5, 5, 5, 5, 5, 5, 5, 5, 5, 5, 5, 5, 5, 5, 5, 5, 5, 5, 5, 5, 5, 5, 5, 5, 5, 5, 5, 5, 5, 5,
            5, 5, 5, 5, 5, 5, 5, 5, 5, 5, 5, 5, 5, 5, 5, 5, 5, 5, 5, 5, 5, 5, 5, 5, 5, 5, 5, 5, 5, 5, 5, 5, 5, 5, 5, 5, 5, 5, 5, 5],
         "height":25,
         "id":1,
         "name":"Layer0",
         "opacity":1,
         "type":"tilelayer",
         "visible":true,
         "width":40,
         "x":0,
         "y":0
        }],
 "nextlayerid":5,
 "nextobjectid":8,
 "orientation":"orthogonal",
 "renderorder":"right-down",
 "tiledversion":"1.11.1",
 "tileheight":32,
 "tilesets":[
        {
         "columns":12,
         "firstgid":1,
         "image":"..\/img\/grid.png",
         "imageheight":256,
         "imagewidth":384,
         "margin":0,
         "name":"Main",
         "spacing":0,
         "tilecount":96,
         "tileheight":32,
         "tiles":[
                {
                 "id":4,
                 "properties":[
                        {
                         "name":"ground_angle",
                         "type":"float",
                         "value":0
                        }, 
                        {
                         "name":"hwmap",
                         "type":"int",
                         "value":0
                        }, 
                        {
                         "name":"solid",
                         "type":"bool",
                         "value":true
                        }]
                }, 
                {
                 "id":5,
                 "properties":[
                        {
                         "name":"flipmap",
                         "type":"bool",
                         "value":false
                        }, 
                        {
                         "name":"ground_angle",
                         "type":"float",
                         "value":3.926990817
                        }, 
                        {
                         "name":"hwmap",
                         "type":"int",
                         "value":4
                        }, 
                        {
                         "name":"solid",
                         "type":"bool",
                         "value":true
                        }]
                }, 
                {
                 "id":6,
                 "properties":[
                        {
                         "name":"flipmap",
                         "type":"bool",
                         "value":false
                        }, 
                        {
                         "name":"ground_angle",
                         "type":"float",
                         "value":3.769911184
                        }, 
                        {
                         "name":"hwmap",
                         "type":"int",
                         "value":3
                        }, 
                        {
                         "name":"solid",
                         "type":"bool",
                         "value":true
                        }]
                }, 
                {
                 "id":7,
                 "properties":[
                        {
                         "name":"flipmap",
                         "type":"bool",
                         "value":false
                        }, 
                        {
                         "name":"ground_angle",
                         "type":"float",
                         "value":3.298672286
                        }, 
                        {
                         "name":"hwmap",
                         "type":"int",
                         "value":2
                        }, 
                        {
                         "name":"solid",
                         "type":"bool",
                         "value":true
                        }]
                }, 
                {
                 "id":8,
                 "properties":[
                        {
                         "name":"flipmap",
                         "type":"bool",
                         "value":true
                        }, 
                        {
                         "name":"ground_angle",
                         "type":"float",
                         "value":2.984513021
                        }, 
                        {
                         "name":"hwmap",
                         "type":"int",
                         "value":2
                        }, 
                        {
                         "name":"solid",
                         "type":"bool",
                         "value":true
                        }]
                }, 
                {
                 "id":9,
                 "properties":[
                        {
                         "name":"flipmap",
                         "type":"bool",
                         "value":true
                        }, 
                        {
                         "name":"ground_angle",
                         "type":"float",
                         "value":2.513274123
                        }, 
                        {
                         "name":"hwmap",
                         "type":"int",
                         "value":3
                        }, 
                        {
                         "name":"solid",
                         "type":"bool",
                         "value":true
                        }]
                }, 
                {
                 "id":10,
                 "properties":[
                        {
                         "name":"flipmap",
                         "type":"bool",
                         "value":true
                        }, 
                        {
                         "name":"ground_angle",
                         "type":"float",
                         "value":2.35619449
                        }, 
                        {
                         "name":"hwmap",
                         "type":"int",
                         "value":4
                        }, 
                        {
                         "name":"solid",
                         "type":"bool",
                         "value":true
                        }]
                }, 
                {
                 "id":12,
                 "properties":[
                        {
                         "name":"ground_angle",
                         "type":"int",
                         "value":0
                        }, 
                        {
                         "name":"hwmap",
                         "type":"int",
                         "value":0
                        }, 
                        {
                         "name":"solid",
                         "type":"bool",
                         "value":true
                        }]
                }, 
                {
                 "id":16,
                 "properties":[
                        {
                         "name":"flipmap",
                         "type":"bool",
                         "value":false
                        }, 
                        {
                         "name":"ground_angle",
                         "type":"float",
                         "value":4.188790205
                        }, 
                        {
                         "name":"hwmap",
                         "type":"int",
                         "value":6
                        }, 
                        {
                         "name":"solid",
                         "type":"bool",
                         "value":true
                        }]
                }, 
                {
                 "id":17,
                 "properties":[
                        {
                         "name":"flipmap",
                         "type":"bool",
                         "value":false
                        }, 
                        {
                         "name":"ground_angle",
                         "type":"float",
                         "value":3.926990817
                        }, 
                        {
                         "name":"hwmap",
                         "type":"int",
                         "value":5
                        }, 
                        {
                         "name":"solid",
                         "type":"bool",
                         "value":true
                        }]
                }, 
                {
                 "id":22,
                 "properties":[
                        {
                         "name":"flipmap",
                         "type":"bool",
                         "value":true
                        }, 
                        {
                         "name":"ground_angle",
                         "type":"float",
                         "value":2.35619449
                        }, 
                        {
                         "name":"hwmap",
                         "type":"int",
                         "value":5
                        }, 
                        {
                         "name":"solid",
                         "type":"bool",
                         "value":true
                        }]
                }, 
                {
                 "id":23,
                 "properties":[
                        {
                         "name":"flipmap",
                         "type":"bool",
                         "value":true
                        }, 
                        {
                         "name":"ground_angle",
                         "type":"float",
                         "value":2.094395102
                        }, 
                        {
                         "name":"hwmap",
                         "type":"int",
                         "value":6
                        }, 
                        {
                         "name":"solid",
                         "type":"bool",
                         "value":true
                        }]
                }, 
                {
                 "id":28,
                 "properties":[
                        {
                         "name":"flipmap",
                         "type":"bool",
                         "value":false
                        }, 
                        {
                         "name":"ground_angle",
                         "type":"float",
                         "value":4.398229715
                        }, 
                        {
                         "name":"hwmap",
                         "type":"int",
                         "value":7
                        }, 
                        {
                         "name":"solid",
                         "type":"bool",
                         "value":true
                        }]
                }, 
                {
                 "id":35,
                 "properties":[
                        {
                         "name":"flipmap",
                         "type":"bool",
                         "value":true
                        }, 
                        {
                         "name":"ground_angle",
                         "type":"float",
                         "value":1.884955592
                        }, 
                        {
                         "name":"hwmap",
                         "type":"int",
                         "value":7
                        }, 
                        {
                         "name":"solid",
                         "type":"bool",
                         "value":true
                        }]
                }, 
                {
                 "id":36,
                 "properties":[
                        {
                         "name":"ground_angle",
                         "type":"float",
                         "value":0.78539816
                        }, 
                        {
                         "name":"hwmap",
                         "type":"int",
                         "value":1
                        }, 
                        {
                         "name":"solid",
                         "type":"bool",
                         "value":true
                        }]
                }, 
                {
                 "id":37,
                 "properties":[
                        {
                         "name":"flipmap",
                         "type":"bool",
                         "value":true
                        }, 
                        {
                         "name":"ground_angle",
                         "type":"float",
                         "value":5.49778714
                        }, 
                        {
                         "name":"hwmap",
                         "type":"int",
                         "value":1
                        }, 
                        {
                         "name":"solid",
                         "type":"bool",
                         "value":true
                        }]
                }, 
                {
                 "id":40,
                 "properties":[
                        {
                         "name":"flipmap",
                         "type":"bool",
                         "value":false
                        }, 
                        {
                         "name":"ground_angle",
                         "type":"float",
                         "value":4.569589314
                        }, 
                        {
                         "name":"hwmap",
                         "type":"int",
                         "value":8
                        }, 
                        {
                         "name":"solid",
                         "type":"bool",
                         "value":true
                        }]
                }, 
                {
                 "id":47,
                 "properties":[
                        {
                         "name":"flipmap",
                         "type":"bool",
                         "value":true
                        }, 
                        {
                         "name":"ground_angle",
                         "type":"float",
                         "value":1.713595993
                        }, 
                        {
                         "name":"hwmap",
                         "type":"int",
                         "value":8
                        }, 
                        {
                         "name":"solid",
                         "type":"bool",
                         "value":true
                        }]
                }, 
                {
                 "id":48,
                 "properties":[
                        {
                         "name":"flipmap",
                         "type":"bool",
                         "value":true
                        }, 
                        {
                         "name":"ground_angle",
                         "type":"float",
                         "value":4.71238898
                        }, 
                        {
                         "name":"hwmap",
                         "type":"int",
                         "value":9
                        }, 
                        {
                         "name":"solid",
                         "type":"bool",
                         "value":true
                        }]
                }, 
                {
                 "id":49,
                 "properties":[
                        {
                         "name":"ground_angle",
                         "type":"float",
                         "value":1.570796327
                        }, 
                        {
                         "name":"hwmap",
                         "type":"int",
                         "value":9
                        }, 
                        {
                         "name":"solid",
                         "type":"bool",
                         "value":true
                        }]
                }, 
                {
                 "id":52,
                 "properties":[
                        {
                         "name":"flipmap",
                         "type":"bool",
                         "value":true
                        }, 
                        {
                         "name":"ground_angle",
                         "type":"float",
                         "value":4.855188646
                        }, 
                        {
                         "name":"hwmap",
                         "type":"int",
                         "value":8
                        }, 
                        {
                         "name":"solid",
                         "type":"bool",
                         "value":true
                        }]
                }, 
                {
                 "id":59,
                 "properties":[
                        {
                         "name":"ground_angle",
                         "type":"float",
                         "value":1.42799666
                        }, 
                        {
                         "name":"hwmap",
                         "type":"int",
                         "value":8
                        }, 
                        {
                         "name":"solid",
                         "type":"bool",
                         "value":true
                        }]
                }, 
                {
                 "id":64,
                 "properties":[
                        {
                         "name":"flipmap",
                         "type":"bool",
                         "value":true
                        }, 
                        {
                         "name":"ground_angle",
                         "type":"float",
                         "value":5.026548246
                        }, 
                        {
                         "name":"hwmap",
                         "type":"int",
                         "value":7
                        }, 
                        {
                         "name":"solid",
                         "type":"bool",
                         "value":true
                        }]
                }, 
                {
                 "id":71,
                 "properties":[
                        {
                         "name":"ground_angle",
                         "type":"float",
                         "value":1.25663706
                        }, 
                        {
                         "name":"hwmap",
                         "type":"int",
                         "value":7
                        }, 
                        {
                         "name":"solid",
                         "type":"bool",
                         "value":true
                        }]
                }, 
                {
                 "id":76,
                 "properties":[
                        {
                         "name":"flipmap",
                         "type":"bool",
                         "value":true
                        }, 
                        {
                         "name":"ground_angle",
                         "type":"float",
                         "value":5.235987756
                        }, 
                        {
                         "name":"hwmap",
                         "type":"int",
                         "value":6
                        }, 
                        {
                         "name":"solid",
                         "type":"bool",
                         "value":true
                        }]
                }, 
                {
                 "id":77,
                 "properties":[
                        {
                         "name":"flipmap",
                         "type":"bool",
                         "value":true
                        }, 
                        {
                         "name":"ground_angle",
                         "type":"float",
                         "value":5.497787144
                        }, 
                        {
                         "name":"hwmap",
                         "type":"int",
                         "value":5
                        }, 
                        {
                         "name":"solid",
                         "type":"bool",
                         "value":true
                        }]
                }, 
                {
                 "id":82,
                 "properties":[
                        {
                         "name":"ground_angle",
                         "type":"float",
                         "value":0.78539816
                        }, 
                        {
                         "name":"hwmap",
                         "type":"int",
                         "value":5
                        }, 
                        {
                         "name":"solid",
                         "type":"bool",
                         "value":true
                        }]
                }, 
                {
                 "id":83,
                 "properties":[
                        {
                         "name":"ground_angle",
                         "type":"float",
                         "value":1.04719755
                        }, 
                        {
                         "name":"hwmap",
                         "type":"int",
                         "value":6
                        }, 
                        {
                         "name":"solid",
                         "type":"bool",
                         "value":true
                        }]
                }, 
                {
                 "id":88,
                 "properties":[
                        {
                         "name":"ground_angle",
                         "type":"float",
                         "value":0
                        }, 
                        {
                         "name":"hwmap",
                         "type":"int",
                         "value":0
                        }, 
                        {
                         "name":"solid",
                         "type":"bool",
                         "value":true
                        }]
                }, 
                {
                 "id":89,
                 "properties":[
                        {
                         "name":"flipmap",
                         "type":"bool",
                         "value":true
                        }, 
                        {
                         "name":"ground_angle",
                         "type":"float",
                         "value":5.497787144
                        }, 
                        {
                         "name":"hwmap",
                         "type":"int",
                         "value":4
                        }, 
                        {
                         "name":"solid",
                         "type":"bool",
                         "value":true
                        }]
                }, 
                {
                 "id":90,
                 "properties":[
                        {
                         "name":"flipmap",
                         "type":"bool",
                         "value":true
                        }, 
                        {
                         "name":"ground_angle",
                         "type":"float",
                         "value":5.654866776
                        }, 
                        {
                         "name":"hwmap",
                         "type":"int",
                         "value":3
                        }, 
                        {
                         "name":"solid",
                         "type":"bool",
                         "value":true
                        }]
                }, 
                {
                 "id":91,
                 "properties":[
                        {
                         "name":"flipmap",
                         "type":"bool",
                         "value":true
                        }, 
                        {
                         "name":"ground_angle",
                         "type":"float",
                         "value":6.126105675
                        }, 
                        {
                         "name":"hwmap",
                         "type":"int",
                         "value":2
                        }, 
                        {
                         "name":"solid",
                         "type":"bool",
                         "value":true
                        }]
                }, 
                {
                 "id":92,
                 "properties":[
                        {
                         "name":"ground_angle",
                         "type":"float",
                         "value":0.15707963
                        }, 
                        {
                         "name":"hwmap",
                         "type":"int",
                         "value":2
                        }, 
                        {
                         "name":"solid",
                         "type":"bool",
                         "value":true
                        }]
                }, 
                {
                 "id":93,
                 "properties":[
                        {
                         "name":"ground_angle",
                         "type":"float",
                         "value":0.62831853
                        }, 
                        {
                         "name":"hwmap",
                         "type":"int",
                         "value":3
                        }, 
                        {
                         "name":"solid",
                         "type":"bool",
                         "value":true
                        }]
                }, 
                {
                 "id":94,
                 "properties":[
                        {
                         "name":"ground_angle",
                         "type":"float",
                         "value":0.78539816
                        }, 
                        {
                         "name":"hwmap",
                         "type":"int",
                         "value":4
                        }, 
                        {
                         "name":"solid",
                         "type":"bool",
                         "value":true
                        }]
                }],
         "tilewidth":32
        }],
 "tilewidth":32,
 "type":"map",
 "version":"1.10",
 "width":40
}